README.md
grpclib.py
service_pb2.py
service_pb2_grpc.py
setup.py
python_grpc.egg-info/PKG-INFO
python_grpc.egg-info/SOURCES.txt
python_grpc.egg-info/dependency_links.txt
python_grpc.egg-info/requires.txt
python_grpc.egg-info/top_level.txt