Metadata-Version: 2.1
Name: python-grpc
Version: 0.1.0
Summary: common grpc service
Home-page: https://github.com/ChinaSilence/python-grpc
Author: Anoyi
Author-email: 545544032@qq.com
License: UNKNOWN
Platform: UNKNOWN
Classifier: Programming Language :: Python :: 3
Classifier: License :: OSI Approved :: MIT License
Classifier: Operating System :: OS Independent
